flows/ConfigManager.py
flows/FlowsLogger.py
flows/FlowsManager.py
flows/Global.py
flows/MessageDispatcher.py
flows/__init__.py
flows/__main__.py
flows/recipe
flows/Actions/Action.py
flows/Actions/AdoDBAction.py
flows/Actions/AppendVariableByTimeAction.py
flows/Actions/BufferAction.py
flows/Actions/CheckIfAction.py
flows/Actions/CheckUrlFor200Action.py
flows/Actions/CommandAction.py
flows/Actions/CountAction.py
flows/Actions/FilterAction.py
flows/Actions/GenericCustomAction.py
flows/Actions/GetUrlAction.py
flows/Actions/HashAction.py
flows/Actions/InputAlarmAction.py
flows/Actions/InputCronAction.py
flows/Actions/InputReadFileAction.py
flows/Actions/InputTailAction.py
flows/Actions/InputTimerAction.py
flows/Actions/InputWatchdogAction.py
flows/Actions/LogAction.py
flows/Actions/MailAction.py
flows/Actions/MailIfResponseErrorAction.py
flows/Actions/PassOnInterval.py
flows/Actions/RestartAction.py
flows/Actions/SubstringAction.py
flows/Actions/WebserverAction.py
flows/Actions/__init__.py
flows/Actions/__pycache__/Action.cpython-36.pyc
flows/Actions/__pycache__/AdoDBAction.cpython-36.pyc
flows/Actions/__pycache__/AppendVariableByTimeAction.cpython-36.pyc
flows/Actions/__pycache__/BufferAction.cpython-36.pyc
flows/Actions/__pycache__/CheckIfAction.cpython-36.pyc
flows/Actions/__pycache__/CheckUrlFor200Action.cpython-36.pyc
flows/Actions/__pycache__/CommandAction.cpython-36.pyc
flows/Actions/__pycache__/CountAction.cpython-36.pyc
flows/Actions/__pycache__/FilterAction.cpython-36.pyc
flows/Actions/__pycache__/GenericCustomAction.cpython-36.pyc
flows/Actions/__pycache__/GetUrlAction.cpython-36.pyc
flows/Actions/__pycache__/HashAction.cpython-36.pyc
flows/Actions/__pycache__/InputAlarmAction.cpython-36.pyc
flows/Actions/__pycache__/InputCronAction.cpython-36.pyc
flows/Actions/__pycache__/InputReadFileAction.cpython-36.pyc
flows/Actions/__pycache__/InputTailAction.cpython-36.pyc
flows-1.2.1.dist-info/DESCRIPTION.rst
flows-1.2.1.dist-info/METADATA
flows-1.2.1.dist-info/RECORD
flows-1.2.1.dist-info/WHEEL
flows-1.2.1.dist-info/entry_points.txt
flows-1.2.1.dist-info/metadata.json
flows-1.2.1.dist-info/top_level.txt
